{
  "generated_at": "2026-05-14T04:05:58.364Z",
  "mode": "live",
  "ttl_seconds": 900,
  "base_url": "https://us-central1-green-segment-491604-j8.cloudfunctions.net/codDashboard",
  "entries": [
    {
      "cache_key": "war-room__default__days_7",
      "url": "https://us-central1-green-segment-491604-j8.cloudfunctions.net/codDashboard?page=war-room&query=default&days=7",
      "status": "OK",
      "row_count": 2
    },
    {
      "cache_key": "war-room__default__days_14",
      "url": "https://us-central1-green-segment-491604-j8.cloudfunctions.net/codDashboard?page=war-room&query=default&days=14",
      "status": "OK",
      "row_count": 2
    },
    {
      "cache_key": "war-room__default__days_30",
      "url": "https://us-central1-green-segment-491604-j8.cloudfunctions.net/codDashboard?page=war-room&query=default&days=30",
      "status": "OK",
      "row_count": 2
    },
    {
      "cache_key": "war-room__dailyRevenue__days_7",
      "url": "https://us-central1-green-segment-491604-j8.cloudfunctions.net/codDashboard?page=war-room&query=dailyRevenue&days=7",
      "status": "OK",
      "row_count": 31
    },
    {
      "cache_key": "war-room__dailyRevenue__days_14",
      "url": "https://us-central1-green-segment-491604-j8.cloudfunctions.net/codDashboard?page=war-room&query=dailyRevenue&days=14",
      "status": "OK",
      "row_count": 31
    },
    {
      "cache_key": "war-room__dailyRevenue__days_30",
      "url": "https://us-central1-green-segment-491604-j8.cloudfunctions.net/codDashboard?page=war-room&query=dailyRevenue&days=30",
      "status": "OK",
      "row_count": 31
    },
    {
      "cache_key": "war-room__staleness",
      "url": "https://us-central1-green-segment-491604-j8.cloudfunctions.net/codDashboard?page=war-room&query=staleness",
      "status": "OK",
      "row_count": 3
    },
    {
      "cache_key": "war-room__leakDetection__days_7",
      "url": "https://us-central1-green-segment-491604-j8.cloudfunctions.net/codDashboard?page=war-room&query=leakDetection&days=7",
      "status": "OK",
      "row_count": 3
    },
    {
      "cache_key": "war-room__leakDetection__days_14",
      "url": "https://us-central1-green-segment-491604-j8.cloudfunctions.net/codDashboard?page=war-room&query=leakDetection&days=14",
      "status": "OK",
      "row_count": 3
    },
    {
      "cache_key": "war-room__leakDetection__days_30",
      "url": "https://us-central1-green-segment-491604-j8.cloudfunctions.net/codDashboard?page=war-room&query=leakDetection&days=30",
      "status": "OK",
      "row_count": 3
    },
    {
      "cache_key": "war-room__dailyRevenueStack__days_7",
      "url": "https://us-central1-green-segment-491604-j8.cloudfunctions.net/codDashboard?page=war-room&query=dailyRevenueStack&days=7",
      "status": "OK",
      "row_count": 14
    },
    {
      "cache_key": "war-room__dailyRevenueStack__days_14",
      "url": "https://us-central1-green-segment-491604-j8.cloudfunctions.net/codDashboard?page=war-room&query=dailyRevenueStack&days=14",
      "status": "OK",
      "row_count": 14
    },
    {
      "cache_key": "war-room__dailyRevenueStack__days_30",
      "url": "https://us-central1-green-segment-491604-j8.cloudfunctions.net/codDashboard?page=war-room&query=dailyRevenueStack&days=30",
      "status": "OK",
      "row_count": 14
    },
    {
      "cache_key": "war-room__weeklyDailyBreakdown",
      "url": "https://us-central1-green-segment-491604-j8.cloudfunctions.net/codDashboard?page=war-room&query=weeklyDailyBreakdown",
      "status": "OK",
      "row_count": 14
    }
  ]
}