{"query_key":"ads-meta__demographicsAgeGender__days_14","page":"ads-meta","query_name":"demographicsAgeGender","params":{"days":14},"fetched_at":"2026-05-13T18:50:44.548Z","ttl_seconds":900,"row_count":18,"rows":[{"age":"45-54","gender":"female","spend":83665.28,"impressions":808469,"clicks":40992,"purchases":200,"revenue":72562.38,"leads":723,"landing_page_views":8511,"roas":0.87,"cpa":418.33,"ctr":5.07,"cpm":103.49},{"age":"55-64","gender":"female","spend":73044.8,"impressions":576937,"clicks":33439,"purchases":156,"revenue":8374,"leads":622,"landing_page_views":7495,"roas":0.11,"cpa":468.24,"ctr":5.8,"cpm":126.61},{"age":"55-64","gender":"male","spend":57542.21,"impressions":736985,"clicks":42920,"purchases":108,"revenue":3186,"leads":381,"landing_page_views":6595,"roas":0.06,"cpa":532.8,"ctr":5.82,"cpm":78.08},{"age":"45-54","gender":"male","spend":53265.6,"impressions":974475,"clicks":61792,"purchases":192,"revenue":7936.78,"leads":364,"landing_page_views":6809,"roas":0.15,"cpa":277.43,"ctr":6.34,"cpm":54.66},{"age":"35-44","gender":"female","spend":44018.21,"impressions":712496,"clicks":35765,"purchases":92,"revenue":2754,"leads":300,"landing_page_views":5043,"roas":0.06,"cpa":478.46,"ctr":5.02,"cpm":61.78},{"age":"65+","gender":"male","spend":40679.53,"impressions":468575,"clicks":30434,"purchases":94,"revenue":32868,"leads":281,"landing_page_views":4452,"roas":0.81,"cpa":432.76,"ctr":6.5,"cpm":86.82},{"age":"65+","gender":"female","spend":38733.67,"impressions":342187,"clicks":23247,"purchases":102,"revenue":3056.14,"leads":350,"landing_page_views":4688,"roas":0.08,"cpa":379.74,"ctr":6.79,"cpm":113.19},{"age":"35-44","gender":"male","spend":34888.97,"impressions":1151766,"clicks":94464,"purchases":84,"revenue":12448.7,"leads":244,"landing_page_views":6120,"roas":0.36,"cpa":415.34,"ctr":8.2,"cpm":30.29},{"age":"25-34","gender":"male","spend":13313.1,"impressions":539102,"clicks":45545,"purchases":18,"revenue":540,"leads":86,"landing_page_views":2881,"roas":0.04,"cpa":739.62,"ctr":8.45,"cpm":24.69},{"age":"25-34","gender":"female","spend":9830.01,"impressions":206158,"clicks":9886,"purchases":6,"revenue":162,"leads":61,"landing_page_views":1465,"roas":0.02,"cpa":1638.34,"ctr":4.8,"cpm":47.68},{"age":"45-54","gender":"unknown","spend":1686.64,"impressions":23120,"clicks":1257,"purchases":2,"revenue":108,"leads":14,"landing_page_views":199,"roas":0.06,"cpa":843.32,"ctr":5.44,"cpm":72.95},{"age":"55-64","gender":"unknown","spend":1667.27,"impressions":17664,"clicks":906,"purchases":2,"revenue":108,"leads":14,"landing_page_views":194,"roas":0.06,"cpa":833.64,"ctr":5.13,"cpm":94.39},{"age":"65+","gender":"unknown","spend":1300.49,"impressions":11154,"clicks":610,"purchases":0,"revenue":0,"leads":4,"landing_page_views":128,"roas":0,"cpa":null,"ctr":5.47,"cpm":116.59},{"age":"35-44","gender":"unknown","spend":1100.44,"impressions":20255,"clicks":1332,"purchases":0,"revenue":0,"leads":10,"landing_page_views":160,"roas":0,"cpa":null,"ctr":6.58,"cpm":54.33},{"age":"18-24","gender":"male","spend":477.97,"impressions":13613,"clicks":1550,"purchases":0,"revenue":0,"leads":2,"landing_page_views":102,"roas":0,"cpa":null,"ctr":11.39,"cpm":35.11},{"age":"25-34","gender":"unknown","spend":340.4,"impressions":5304,"clicks":320,"purchases":0,"revenue":0,"leads":4,"landing_page_views":24,"roas":0,"cpa":null,"ctr":6.03,"cpm":64.18},{"age":"18-24","gender":"female","spend":225.88,"impressions":2604,"clicks":184,"purchases":0,"revenue":0,"leads":0,"landing_page_views":18,"roas":0,"cpa":null,"ctr":7.07,"cpm":86.74},{"age":"18-24","gender":"unknown","spend":17.06,"impressions":154,"clicks":20,"purchases":0,"revenue":0,"leads":0,"landing_page_views":2,"roas":0,"cpa":null,"ctr":12.99,"cpm":110.8}]}